weak_ner/__init__.py
weak_ner/data/__init__.py
weak_ner/data/read_lines.py
weak_ner/logic/__init__.py
weak_ner/logic/entities.py
weak_ner/logic/param.py
weak_ner/logic/utils.py
weak_ner/logic/list_pattern_model/__init__.py
weak_ner/logic/list_pattern_model/list_weak_model.py
weak_ner/logic/pipeline_builder/__init__.py
weak_ner/logic/pipeline_builder/pipeline_weak_labeling.py
weak_ner/logic/rule_based_model/__init__.py
weak_ner/logic/rule_based_model/name_location_rules.py
weak_ner/logic/rule_based_model/rule_weak_model.py
weak_ner/presentation/__init__.py
weak_ner/presentation/weak_labels.py
weak_ner-0.0.1.dist-info/METADATA
weak_ner-0.0.1.dist-info/WHEEL
weak_ner-0.0.1.dist-info/top_level.txt
weak_ner-0.0.1.dist-info/RECORD
