Metadata-Version: 2.1
Name: weak-ner
Version: 0.0.1
Summary: Weak NER Model
Home-page: UNKNOWN
Author: Data & Analytics Research
Author-email: analytics.dar@take.net
Maintainer: daresearch
Maintainer-email: anaytics.dar@take.net
License: MIT License
Keywords: ner,named entity recognition,weak modeling
Platform: UNKNOWN
Classifier: Programming Language :: Python :: 3
Classifier: Operating System :: OS Independent
Requires-Dist: pytest (==5.3.5)
Requires-Dist: unidecode (==1.1.1)
Requires-Dist: take-text-preprocess (==0.0.4)
Requires-Dist: regex (==2021.8.28)
